WallGoCollision/_version.py
WallGoCollision/__init__.py
WallGoCollision/_WallGoCollision.cpython-311-darwin.so
wallgocollision-1.1.1.dist-info/RECORD
wallgocollision-1.1.1.dist-info/WHEEL
wallgocollision-1.1.1.dist-info/METADATA
wallgocollision-1.1.1.dist-info/licenses/LICENSE
