Metadata-Version: 2.1
Name: WallGoCollision
Version: 1.1.1
Summary: Python bindings for WallGo Collision module
License: GPL 3.0
Requires-Python: >=3.10
Provides-Extra: tests
Requires-Dist: pytest>=7.2.2; extra == "tests"
Provides-Extra: docs
Requires-Dist: myst_parser; extra == "docs"
Requires-Dist: sphinx; extra == "docs"
Requires-Dist: sphinx-rtd-theme; extra == "docs"
Requires-Dist: sphinxcontrib-bibtex; extra == "docs"
